<?xml version="1.0" encoding="utf-8"?>
<markers><country lat="48.3663" lng="10.9046" zoom="11" name="SWA Rad" hotline="+493069205046" domain="ag" country="DE" country_name="Germany" terms="http://www.swa-rad.de/de/agb/" policy="" website="http://www.swa-rad.de/"><city uid="178" lat="48.3647" lng="10.8916" zoom="13" maps_icon="swarad" alias="augsburg" break="0" name="Augsburg"><place uid="81900" lat="48.3498536642391" lng="10.9177869558334" name="Zoo / Botanischer Garten" spot="1" number="4550" bikes="4" terminal_type="stele" bike_numbers="92274,92272,92271,92196" bike_types='{"14":4}' /><place uid="81902" lat="48.3803117930941" lng="10.8556240797043" name="Kriegshaber" spot="1" number="4551" bikes="5" terminal_type="stele" bike_numbers="92134,92253,92251,92233,92217" bike_types='{"14":5}' /><place uid="81903" lat="48.3098876349913" lng="10.8935236930847" name="Haunstetten-West" spot="1" number="4552" bikes="2" terminal_type="stele" bike_numbers="92317,92237" bike_types='{"14":2}' /><place uid="81905" lat="48.3560921851444" lng="10.9639692306519" name="P+R Friedberg-West" spot="1" number="4553" bikes="5" terminal_type="stele" bike_numbers="92299,92298,92297,92296,92226" bike_types='{"14":5}' /><place uid="81906" lat="48.4027463442209" lng="10.8791470527649" name="Augsburg Nord" spot="1" number="4554" bikes="6" terminal_type="stele" bike_numbers="92295,92283,92282,92232,92230" bike_types='{"14":6}' /><place uid="81907" lat="48.3656374258241" lng="10.9367823600769" name="Lechhausen / Neuer Ostfriedhof" spot="1" number="4555" bikes="6" terminal_type="stele" bike_numbers="92319,92309,92308,92306,92266" bike_types='{"14":6}' /><place uid="81910" lat="48.3686114827689" lng="10.8953636884689" name="Ernst-Reuter-Platz" spot="1" number="4556" bikes="2" terminal_type="stele" bike_numbers="92244,92243" bike_types='{"14":2}' /><place uid="81912" lat="48.3659118517729" lng="10.9049016237259" name="City Galerie" spot="1" number="4557" bikes="5" terminal_type="stele" bike_numbers="92312,92302,92292,92239,92219" bike_types='{"14":5}' /><place uid="81913" lat="48.3810528825441" lng="10.8732461929321" name="Oberhausen Bahnhof" spot="1" number="4558" bikes="8" terminal_type="stele" bike_numbers="92323,92294,92291,92278,92261" bike_types='{"14":8}' /><place uid="81914" lat="48.3710116285639" lng="10.8973860740662" name="Stadtwerke" spot="1" number="4559" bikes="10" terminal_type="stele" bike_numbers="92318,92275,92256,92222,92220" bike_types='{"14":10}' /><place uid="81915" lat="48.372790728218" lng="10.9019391238689" name="Jugendherberge" spot="1" number="4560" bikes="7" terminal_type="stele" bike_numbers="92305,92262,92258,92257,92255" bike_types='{"14":7}' /><place uid="82184" lat="48.3549595047439" lng="10.9026351571083" name="Fachhochschule" spot="1" number="4562" bikes="10" terminal_type="stele" bike_numbers="92329,92328,92327,92326,92324" bike_types='{"14":10}' /><place uid="82244" lat="48.3648943299554" lng="10.8879500627518" name="Hauptbahnhof Radstation" spot="1" number="4561" bikes="2" terminal_type="stele" bike_numbers="92310,92184" bike_types='{"14":2}' /><place uid="117844" lat="48.3694364899625" lng="10.8981049060822" name="Karolinenstraße" spot="1" number="4563" bikes="1" terminal_type="stele" bike_numbers="92231" bike_types='{"14":1}' /><place uid="117845" lat="48.3624083549027" lng="10.8680748939514" name="Pfersee" spot="1" number="4564" bikes="3" terminal_type="stele" bike_numbers="92320,92254,92180" bike_types='{"14":3}' /><place uid="117847" lat="48.3587014427535" lng="10.9032654762268" name="Rotes Tor" spot="1" number="4565" bikes="8" terminal_type="stele" bike_numbers="92325,92304,92260,92250,92249" bike_types='{"14":8}' /><place uid="125765" lat="48.3468517723016" lng="10.9046173095703" name="B&amp;B Hotel Augsburg, Haunstetter Str. 68" spot="1" number="4566" bikes="0" terminal_type="free" /><place uid="135510" lat="48.3670220143844" lng="10.8459144830704" name="Stadtbergen / Altenheim" spot="1" number="4567" bikes="3" terminal_type="stele" bike_numbers="92311,92248,92203" bike_types='{"14":3}' /><place uid="183641" lat="48.367825664353" lng="10.8712935447693" name="Die Junge Werkstatt" spot="1" number="4568" bikes="2" terminal_type="stele" bike_numbers="92303,92301" bike_types='{"14":2}' /><place uid="201960" lat="48.3964850432532" lng="10.9148177504539" name="Hammerschmiede" spot="1" number="4569" bikes="8" terminal_type="stele" bike_numbers="92313,92286,92267,92246,92225" bike_types='{"14":8}' /><place uid="206265" lat="48.38348985062049" lng="10.838978290557861" name="Zentralklinikum" spot="1" number="4570" bikes="3" terminal_type="stele" bike_numbers="92242,92241,92240" bike_types='{"14":3}' /><place uid="206266" lat="48.35543628516476" lng="10.95086932182312" name="Friedberger Straße" spot="1" number="4571" bikes="5" terminal_type="stele" bike_numbers="92315,92314,92307,92265,92227" bike_types='{"14":5}' /><place uid="206267" lat="48.3874443312196" lng="10.9064412117004" name="Schillstraße 98" spot="1" number="4572" bikes="7" terminal_type="stele" bike_numbers="92300,92288,92287,92224,92223" bike_types='{"14":7}' /><place uid="206268" lat="48.3851714330718" lng="10.8803862333298" name="Donauwörther Straße" spot="1" number="4573" bikes="3" terminal_type="stele" bike_numbers="92276,92208,92193" bike_types='{"14":3}' /><place uid="206269" lat="48.3341898289526" lng="10.8988237380981" name="Universität Augsburg" spot="1" number="4574" bikes="6" terminal_type="stele" bike_numbers="92293,92264,92235,92200,92191" bike_types='{"14":6}' /><place uid="206330" lat="48.3193915887" lng="10.9089356660843" name="Haunstetten-Nord" spot="1" number="4575" bikes="7" terminal_type="stele" bike_numbers="92321,92270,92269,92268,92238" bike_types='{"14":7}' /><place uid="262590" lat="48.3659154157366" lng="10.8942532539368" name="Königsplatz" spot="1" number="4577" bikes="6" terminal_type="stele" bike_numbers="92277,92245,92234,92213,92212" bike_types='{"14":6}' /><place uid="301121" lat="48.33855108425232" lng="10.866401195526123" name="Hessing Kliniken" spot="1" number="4578" bikes="5" terminal_type="stele" bike_numbers="92207,92206,92205,92195,92188" bike_types='{"14":5}' /><place uid="305051" lat="48.36498877679432" lng="10.891871452331543" name="Sparkasse Halderstraße" spot="1" number="4579" bikes="4" terminal_type="stele" bike_numbers="92289,92281,92280,92199" bike_types='{"14":4}' /><place uid="434478" lat="48.36544497038046" lng="10.887504816055298" name="MAN" spot="1" number="4580" bikes="2" terminal_type="stele" bike_numbers="92273,92218" bike_types='{"14":2}' /></city></country></markers>